sgui/__init__.py
sgui/sguibuild.py
spelis_sgui-0.1.0.dist-info/LICENSE
spelis_sgui-0.1.0.dist-info/METADATA
spelis_sgui-0.1.0.dist-info/WHEEL
spelis_sgui-0.1.0.dist-info/top_level.txt
spelis_sgui-0.1.0.dist-info/RECORD
