Metadata-Version: 2.2
Name: spelis-sgui
Version: 0.1.0
Summary: Lightweight and easy-to-use Immediate Mode GUI library for Python and Raylib
Home-page: https://github.com/spelis/sgui
Author: Elis Eriksson
Author-email: Elis Eriksson <elis.eriksson.2010@gmail.com>
Project-URL: Homepage, https://github.com/spelis/sgui
Project-URL: Issues, https://github.com/spelis/sgui/issues
Classifier: Programming Language :: Python :: 3
Classifier: License :: OSI Approved :: MIT License
Classifier: Operating System :: OS Independent
Requires-Python: >=3.8
License-File: LICENSE
Requires-Dist: raylib>=5.5.0
Dynamic: author
Dynamic: home-page
Dynamic: requires-python
